<AutickaX>
	<pathway>
		<controlPoints>
			<point X="63.0" Y="120.0"/>
			<point X="71.0" Y="304.0"/>
			<point X="216.0" Y="383.0"/>
			<point X="267.0" Y="205.0"/>
			<point X="284.0" Y="101.0"/>
			<point X="410.0" Y="89.0"/>
			<point X="435.0" Y="248.0"/>
			<point X="473.0" Y="399.0"/>
			<point X="658.0" Y="395.0"/>
			<point X="741.0" Y="262.0"/>
			<point X="667.0" Y="42.0"/>
			<point X="265.0" Y="41.0"/>
		</controlPoints>
	</pathway>
	<entities/>
	<car X="0.0" Y="0.0" textureName="car"/>
	<backgroundTexture>sky</backgroundTexture>
</AutickaX>
